<resources>
    <fonts>
    	<font id="VB_Font_42" filename="fonts/VB_Font_42.fnt"/>
		<font id="VB_Font_52" filename="fonts/VB_Font_52.fnt"/>
		<font id="VB_Font_64" filename="fonts/VB_Font_64.fnt"/>
		<font id="VB_Font_72" filename="fonts/VB_Font_72.fnt"/>
		<font id="Steps_Font" filename="fonts/Steps_Font.fnt"/>
		<font id="Battery_Font" filename="fonts/Battery_Font.fnt"/>
	</fonts>
	
	<drawables>
    	<bitmap id="LauncherIcon" filename="drawables/launcher_icon.png" />
	</drawables>
</resources>